Workbook

Sheet Resumen Ejecutivo
B2: PLAN FINANCIERO COMPARTIDO - INFORME Y CONTROL MENSUAL
B3: Estructura modular para seguimiento de ingresos variables, gastos compartidos e individuales
B5: 1. PARÁMETROS GLOBALES DE INGRESOS
B6: Rol / Titular | C6: Concepto | D6: Monto Base Actual | E6: Monto Proyectado / Escenario | F6: Notas
B7: Diego | C7: Sueldo Base Líquido | D7: 1214038 | E7: =C7 -> Sueldo Base Líquido | F7: Variable / Posible reajuste al alza
B8: Soledad | C8: Aporte / Ingresos Estimados | D8: 0 | E8: =C8 -> Aporte / Ingresos Estimados | F8: Ingreso según chequera electrónica BancoEstado
B9: Total Ingresos Familiares | D9: =SUM(C7:C8) -> 0 | E9: =SUM(D7:D8) -> 1214038 | F9: Consolidado hogar
B11: 2. DISTRIBUCIÓN MENSUAL CONSOLIDADA (COFRES Y COMPROMISOS)
B12: Cofre / Categoría | C12: Responsable Principal | D12: Cuenta / Medio | E12: Monto Mensual | F12: % s/ Ingreso Diego
B13: Vivienda y Compromisos Fijos Diego | C13: Diego | D13: Cuenta Fan | E13: =SUM('Control Gastos'!D7:D16) -> 0 | F13: =D13/$C$7 -> #VALUE!
B14: Operaciones y Logística Huasco | C14: Diego | D14: Tenpo | E14: =SUM('Control Gastos'!D19:D22) -> 0 | F14: =D14/$C$7 -> #VALUE!
B15: Bolsillo Personal (Modo Recuperación) | C15: Diego | D15: Mach | E15: =SUM('Control Gastos'!D25:D25) -> 0 | F15: =D15/$C$7 -> #VALUE!
B16: Ahorro Blindado / Fondo Reserva | C16: Diego | D16: Mercado Pago | E16: =SUM('Control Gastos'!D28:D28) -> 0 | F16: =D16/$C$7 -> #VALUE!
B17: Gastos Hogar & Cuentas Básicas | C17: Soledad | D17: Chequera BancoEstado | E17: =SUM('Control Gastos'!E31:E36) -> 0 | F17: Compromiso Pareja
B18: Tarjeta Smart Visa (Deuda Pareja) | C18: Soledad | D18: BancoEstado | E18: =SUM('Control Gastos'!E38:E38) -> 0 | F18: Compromiso Pareja
B20: 3. BALANCE Y CAPACIDAD DE ABSORCIÓN
B21: Total Gastos Fijos & Aportes Diego | D21: =D13+D14+D15+D16 -> #VALUE! | E21: =C21/$C$7 -> #VALUE! | F21: Compromisos asignados a Diego
B22: Reserva Oxígeno / Margen Libre Diego | D22: =C7-C21 -> #VALUE! | E22: =C22/$C$7 -> #VALUE! | F22: Excedente mensual antes de barrido a Mercado Pago
B23: Total Gastos Asignados Pareja (Promedio) | D23: =D17+D18 -> #VALUE! | E23: - | F23: Gastos básicos hogar + cuota tarjeta

Sheet Control Gastos
B2: REGISTRO DETALLADO DE COSTOS Y COMPROMISOS MENSUALES
B3: Plantilla colaborativa para registrar valores reales mes a mes
B5: ID / Categoría | C5: Concepto / Detalle | D5: Frecuencia / Plazo | E5: Aporte Diego (CLP) | F5: Aporte Pareja (CLP) | G5: Medio / Cuenta | H5: Histórico Jul-26 | I5: Histórico Ago-26 | J5: Histórico Sep-26 | K5: Observaciones
B7: Vivienda | C7: Crédito Hipotecario (Base en UF) | D7: Mensual (1-5) | E7: 365000 | F7: 0 | G7: Cuenta Fan | H7: 372317 | I7: 372558 | J7: 374199 | K7: Diferencial UF pagado por Pareja
B8: Vivienda Huasco | C8: Arriendo Habitación Huasco | D8: Mensual (Día 1) | E8: 95000 | F8: 0 | G8: Cuenta Fan | H8: 95000 | I8: 95000 | J8: 95000 | K8: Base operativa
B9: Vivienda Huasco | C9: Servicios Huasco (Luz y Agua) | D9: Mensual (Variable) | E9: 7000 | F9: 0 | G9: Cuenta Fan | H9: 7000 | I9: 7000 | J9: 7000 | K9: Estimado mensual
B10: Conectividad | C10: Internet + Planes Celular (Diego) | D10: Mensual (10-15) | E10: 40000 | F10: 0 | G10: Cuenta Fan | H10: 40000 | I10: 40000 | J10: 40000 | K10: Conectividad personal
B11: Mascotas | C11: Comida Michis (41.900) | D11: Mensual | E11: 41900 | F11: 0 | G11: Cuenta Fan | H11: 42000 | I11: 0 | J11: 42900 | K11: Asumido por Diego desde Octubre
B12: Mascotas | C12: Arena Sanitaria Michis (23.200) | D12: Mensual | E12: 23200 | F12: 0 | G12: Cuenta Fan | H12: 24900 | I12: 23200 | J12: 0 | K12: Asumido por Diego desde Octubre
B13: Streaming | C13: Netflix | D13: Mensual | E13: 10388 | F13: 0 | G13: Cuenta Fan | H13: 10388 | I13: 10388 | J13: 10388 | K13: Suscripción recurrente
B14: Streaming | C14: Crunchyroll | D14: Mensual | E14: 6490 | F14: 0 | G14: Cuenta Fan | H14: 6490 | I14: 6490 | J14: 6490 | K14: Suscripción recurrente
B15: Salud Cíclica | C15: Eutirox 137 (Ajuste ponderado mensual) | D15: Cada 45 días ($15k) | E15: 10000 | F15: 0 | G15: Cuenta Fan | H15: 10000 | I15: 10000 | J15: 10000 | K15: Ponderación mensual
B16: Salud Cíclica | C16: Rupatadina (Ajuste ponderado mensual) | D16: Cada 28 días ($9.7k) | E16: 10382 | F16: 0 | G16: Cuenta Fan | H16: 9690 | I16: 9690 | J16: 9690 | K16: Ponderación mensual
B17: SUBTOTAL FIJOS DIEGO | E17: =SUM(E7:E16) -> 609360
B19: Operaciones | C19: Pasajes Interregionales (8 viajes) | D19: Mensual | E19: 231500 | F19: 0 | G19: Tenpo | H19: 228500 | I19: 228500 | J19: 228500 | K19: Promedio ajustado con descuentos
B20: Operaciones | C20: Uber (Traslados y retenciones) | D20: Mensual | E20: 25000 | F20: 0 | G20: Tenpo | H20: 25000 | I20: 25000 | J20: 25000 | K20: Margen de seguridad PayU
B21: Operaciones | C21: Metro Valparaíso (EFE) | D21: Mensual | E21: 10000 | F21: 0 | G21: Tenpo | H21: 10000 | I21: 10000 | J21: 10000 | K21: Recarga mensual
B22: Operaciones | C22: Snacks Turno (Galletas + Energéticas) | D22: Mensual (4 turnos) | E22: 33500 | F22: 0 | G22: Tenpo | H22: 32000 | I22: 32000 | J22: 32000 | K22: ~$8.3k por turno en Huasco
B23: SUBTOTAL OPERACIONES TENPO | E23: =SUM(E19:E22) -> 300000
B25: Bolsillo | C25: Asignación Semanal ($35.000 x 4) | D25: Semanal (Lunes) | E25: 140000 | F25: 0 | G25: Mach | H25: 180000 | I25: 180000 | J25: 180000 | K25: Ajustado a modo recuperación
B26: SUBTOTAL BOLSILLO MACH | E26: =SUM(E25:E25) -> 140000
B28: Ahorro | C28: Fondo de Emergencia / Reserva Base | D28: Mensual (Día 1) | E28: 130000 | F28: 0 | G28: Mercado Pago | H28: 130000 | I28: 130000 | J28: 130000 | K28: Interés diario compuesto
B29: SUBTOTAL AHORRO MERCADO PAGO | E29: =SUM(E28:E28) -> 130000
B31: Hogar Limache | C31: Luz (CGE / Chilquinta) | D31: Mensual | E31: 0 | F31: 33099 | G31: BancoEstado | H31: 54618 | I31: 27604 | J31: 17075 | K31: Promedio trimestral variable
B32: Hogar Limache | C32: Agua (Esval) | D32: Mensual | E32: 0 | F32: 7843 | G32: BancoEstado | H32: 8490 | I32: 7580 | J32: 7460 | K32: Promedio trimestral
B33: Hogar Limache | C33: Gas (Lipigas / Abastible) | D33: Mensual | E33: 0 | F33: 25867 | G33: BancoEstado | H33: 27800 | I33: 27600 | J33: 22200 | K33: Promedio trimestral
B34: Conectividad | C34: Plan Claro (Pareja) | D34: Mensual | E34: 0 | F34: 9922 | G34: BancoEstado | H34: 9914 | I34: 9914 | J34: 9938 | K34: Plan celular pareja
B35: Hogar Limache | C35: Gasto Común Condominio | D35: Mensual | E35: 0 | F35: 52094 | G35: BancoEstado | H35: 49957 | I35: 52597 | J35: 53728 | K35: Promedio trimestral
B36: Alimentación | C36: Supermercado Hogar Limache | D36: Mensual | E36: 0 | F36: 120000 | G36: BancoEstado | H36: 119800 | I36: 0 | J36: 0 | K36: Presupuesto estimado hogar
B37: SUBTOTAL GASTOS BÁSICOS HOGAR (PAREJA) | F37: =SUM(F31:F36) -> 248825
B39: Compromisos | C39: Tarjeta Smart Visa | D39: Mensual | E39: 0 | F39: 106667 | G39: BancoEstado | H39: 100000 | I39: 110000 | J39: 110000 | K39: Pago mensual recurrente
B40: SUBTOTAL COMPROMISOS PAREJA | F40: =SUM(F39:F39) -> 106667

Sheet Simulador Incremento Sueldo
B2: SIMULADOR DE SENSIBILIDAD ANTE ALZA DE SUELDO
B3: Evaluación de escenarios si tu renta líquida se incrementa en los próximos meses
B5: Escenario | C5: Sueldo Líquido Diego | D5: Gastos Fijos + Mascotas | E5: Operaciones Huasco | F5: Bolsillo Semanal | G5: Ahorro Base | H5: Reserva Oxígeno Libre | I5: % Tasa Ahorro Real | J5: Destino Recomendado del Excedente
B6: Base Actual (Mayo) | C6: 1214038 | D6: 609360 | E6: 300000 | F6: 140000 | G6: 130000 | H6: =C6-(D6+E6+F6+G6) -> 34678 | I6: =(G6+H6)/C6 -> 0.13564485 | J6: Reconstruir Mercado Pago
B7: Escenario +$50k | C7: 1264038 | D7: 609360 | E7: 300000 | F7: 160000 | G7: 150000 | H7: =C7-(D7+E7+F7+G7) -> 44678 | I7: =(G7+H7)/C7 -> 0.15401277 | J7: Subir bolsillo a $40k y $20k a ahorro
B8: Escenario +$100k | C8: 1314038 | D8: 609360 | E8: 300000 | F8: 180000 | G8: 180000 | H8: =C8-(D8+E8+F8+G8) -> 44678 | I8: =(G8+H8)/C8 -> 0.17098288 | J8: Volver a bolsillo $45k y reforzar ahorro
B9: Escenario +$150k | C9: 1364038 | D9: 609360 | E9: 300000 | F9: 180000 | G9: 220000 | H9: =C9-(D9+E9+F9+G9) -> 54678 | I9: =(G9+H9)/C9 -> 0.20137122 | J9: Acelerar Fondo Emergencia ($2.1M)
B10: Escenario +$200k | C10: 1414038 | D10: 609360 | E10: 300000 | F10: 180000 | G10: 250000 | H10: =C10-(D10+E10+F10+G10) -> 74678 | I10: =(G10+H10)/C10 -> 0.22961052 | J10: Prepago capital Hipotecario o inversión
